mozilla_taar-0.0.16.dist-info/DESCRIPTION.rst
mozilla_taar-0.0.16.dist-info/METADATA
mozilla_taar-0.0.16.dist-info/RECORD
mozilla_taar-0.0.16.dist-info/WHEEL
mozilla_taar-0.0.16.dist-info/dependency_links.txt
mozilla_taar-0.0.16.dist-info/metadata.json
mozilla_taar-0.0.16.dist-info/top_level.txt
taar/__init__.py
taar/hbase_client.py
taar/profile_fetcher.py
taar/recommenders/__init__.py
taar/recommenders/base_recommender.py
taar/recommenders/collaborative_recommender.py
taar/recommenders/legacy_recommender.py
taar/recommenders/locale_recommender.py
taar/recommenders/recommendation_manager.py
taar/recommenders/similarity_recommender.py
taar/recommenders/utils.py
