Metadata-Version: 2.0
Name: mozilla-taar
Version: 0.0.16
Summary: Telemetry-Aware Addon Recommender
Home-page: https://github.com/mdoglio/taar
Author: Mozilla Foundation
Author-email: fx-data-dev@mozilla.org
License: MPL 2.0
Platform: UNKNOWN
Classifier: Development Status :: 3 - Alpha
Classifier: Environment :: Web Environment :: Mozilla
Classifier: Intended Audience :: Developers
Classifier: License :: OSI Approved :: Mozilla Public License 2.0 (MPL 2.0)
Classifier: Programming Language :: Python
Classifier: Programming Language :: Python :: 3
Classifier: Programming Language :: Python :: 3.5
Classifier: Topic :: Internet :: WWW/HTTP
Classifier: Topic :: Scientific/Engineering :: Information Analysis
Requires-Dist: boto3
Requires-Dist: happybase
Requires-Dist: numpy
Requires-Dist: ply
Requires-Dist: requests
Requires-Dist: scipy
Requires-Dist: six
Requires-Dist: thriftpy
